lsf_runner/__init__.py
lsf_runner/runners.py
lsf_runner/util.py
tests/__init__.py
tests/script.py
tests/test_runner.py
lsf_runner-0.0.5.dist-info/LICENSE
lsf_runner-0.0.5.dist-info/METADATA
lsf_runner-0.0.5.dist-info/WHEEL
lsf_runner-0.0.5.dist-info/top_level.txt
lsf_runner-0.0.5.dist-info/RECORD
