Metadata-Version: 2.1
Name: lsf-runner
Version: 0.0.5
Summary: A package to run experiments on lsf or linux clusters.
Home-page: https://github.com/sebascuri/runner
Author: Sebastian Curi
Author-email: sebascuri@gmail.com
License: MIT
Platform: UNKNOWN
Classifier: Intended Audience :: Developers
Classifier: Topic :: Software Development :: Build Tools
Classifier: Programming Language :: Python :: 3
Classifier: License :: OSI Approved :: MIT License
Classifier: Operating System :: OS Independent
Requires-Python: >=3.6
Provides-Extra: test
Requires-Dist: pytest (<5.1,>=5.0) ; extra == 'test'
Requires-Dist: flake8 (<3.8,>=3.7.8) ; extra == 'test'
Requires-Dist: pydocstyle (==4.0.0) ; extra == 'test'
Requires-Dist: pytest-cov (<3,>=2.7) ; extra == 'test'
Requires-Dist: mypy (>=0.740) ; extra == 'test'
